url_cache/__main__.py
url_cache/common.py
url_cache/core.py
url_cache/dir_cache.py
url_cache/exceptions.py
url_cache/html_utils.py
url_cache/model.py
url_cache/py.typed
url_cache/session.py
url_cache/summary_cache.py
url_cache/utils.py
url_cache/sites/abstract.py
url_cache/sites/all.py
url_cache/sites/stackoverflow.py
url_cache/sites/myanimelist/core.py
url_cache/sites/myanimelist/urls/v4.py
url_cache/sites/youtube/core.py
url_cache/sites/youtube/srt_converter.py
url_cache/sites/youtube/subtitles_downloader.py
url_cache-0.0.9.dist-info/LICENSE
url_cache-0.0.9.dist-info/METADATA
url_cache-0.0.9.dist-info/WHEEL
url_cache-0.0.9.dist-info/entry_points.txt
url_cache-0.0.9.dist-info/top_level.txt
url_cache-0.0.9.dist-info/RECORD
