Metadata-Version: 2.1
Name: url-cache
Version: 0.0.9
Summary: A file system cache which saves URL metadata and summarizes content
Home-page: https://github.com/seanbreckenridge/url_cache
Author: Sean Breckenridge
Author-email: seanbrecke@gmail.com
License: http://www.apache.org/licenses/LICENSE-2.0
Keywords: url cache metadata youtube subtitles
Classifier: License :: OSI Approved :: Apache Software License
Classifier: Programming Language :: Python
Classifier: Programming Language :: Python :: 3
Classifier: Programming Language :: Python :: 3.7
Classifier: Programming Language :: Python :: 3.8
Classifier: Programming Language :: Python :: 3.9
Classifier: Programming Language :: Python :: 3.10
Classifier: Programming Language :: Python :: 3.11
License-File: LICENSE
Requires-Dist: appdirs (>=1.4.4)
Requires-Dist: lassie (>=0.11.11)
Requires-Dist: readability-lxml (>=0.8.1)
Requires-Dist: backoff (>=1.10.0)
Requires-Dist: click (>=7.1.2)
Requires-Dist: requests
Requires-Dist: logzero
Requires-Dist: simplejson
Requires-Dist: pytube (>=11.0.2)
Requires-Dist: lxml (>=4.0.0)
Provides-Extra: testing
Requires-Dist: pytest ; extra == 'testing'
Requires-Dist: mypy ; extra == 'testing'
Requires-Dist: flake8 ; extra == 'testing'
Requires-Dist: vcrpy ; extra == 'testing'
